{
    "intent": "TaskList",
    "required": [
        {
            "QuestionKeyword": [
                "What",
                "Which tasks"
            ]
        },
        {
            "TaskSupplementaryPhrase": [
                "is there",
                "can",
                "are"
            ]
        },
        {
            "TaskListVerb": [
                "do",
                "there"
            ]
        }
    ],
    "optionally": [
        {
            "QuestionIndicator": [
                "?"
            ]
        }
    ]
}